<DOMSymbolItem xmlns:xsi="http://www.w3.org/2001/XMLSchema-instance" xmlns="http://ns.adobe.com/xfl/2008/" name="MC_score" itemID="5640c50d-00000137" lastModified="1447594426">
  <timeline>
    <DOMTimeline name="MC_score">
      <layers>
        <DOMLayer name="M+c" color="#0000FF" current="true" isSelected="true" autoNamed="false">
          <frames>
            <DOMFrame index="0" keyMode="9728">
              <elements>
                <DOMShape isDrawingObject="true">
                  <matrix>
                    <Matrix a="2.85386657714844" d="2.85386657714844" tx="14.85" ty="0.05"/>
                  </matrix>
                  <fills>
                    <FillStyle index="1">
                      <SolidColor color="#73400B"/>
                    </FillStyle>
                  </fills>
                  <edges>
                    <Edge fillStyle1="1" edges="!27 32|27 1!27 1|229 1!229 1|229 32!229 32[205 86 163 131!163 131[221 183 256 220!256 220|233 243!233 243|141 154!141 154[86 207 15 241!15 241|0 214!0 214[69 177 117 132!117 132[164 87 192 32!192 32|27 32"/>
                    <Edge cubics="!27 32(;27,32 27,1 27,1p27 32 27 1);"/>
                    <Edge cubics="!27 1(;27,1 229,1 229,1p27 1 229 1);"/>
                    <Edge cubics="!229 1(;229,1 229,32 229,32p229 1 229 32);"/>
                    <Edge cubics="!229 32(;214,66 192,100 163,131q229 32Q205 86q163 131);"/>
                    <Edge cubics="!163 131(;196,161 227,190 256,220q163 131Q221 183q256 220);"/>
                    <Edge cubics="!256 220(;256,220 233,243 233,243q256 220 233 243);"/>
                    <Edge cubics="!233 243(;202,212 171,182 141,154q233 243 141 154);"/>
                    <Edge cubics="!141 154(;104,189 62,218 15,241q141 154Q86 207q15 241);"/>
                    <Edge cubics="!15 241(;15,241 0,214 0,214q15 241 0 214);"/>
                    <Edge cubics="!0 214(;45,190 84,163 117,132q0 214Q69 177q117 132);"/>
                    <Edge cubics="!117 132(;149,101 174,67 192,32q117 132Q164 87q192 32);"/>
                    <Edge cubics="!192 32(;192,32 27,32 27,32q192 32 27 32)27,32;"/>
                  </edges>
                </DOMShape>
                <DOMShape isDrawingObject="true">
                  <matrix>
                    <Matrix a="2.85386657714844" d="2.85386657714844" tx="14.85" ty="0.05"/>
                  </matrix>
                  <fills>
                    <FillStyle index="1">
                      <SolidColor color="#73400B"/>
                    </FillStyle>
                  </fills>
                  <edges>
                    <Edge fillStyle1="1" edges="!293 7|520 6!520 6|521 227!521 227|293 227!293 227|293 197!293 197|487 196!487 196|486 36!486 36|293 37!293 37|293 7"/>
                    <Edge cubics="!293 7(293,7;293,7 520,6 520,6p293 7 520 6)520,6;"/>
                    <Edge cubics="!520 6(;520,6 521,227 521,227p520 6 521 227);"/>
                    <Edge cubics="!521 227(;521,227 293,227 293,227p521 227 293 227);"/>
                    <Edge cubics="!293 227(;293,227 293,197 293,197p293 227 293 197);"/>
                    <Edge cubics="!293 197(;293,197 487,196 487,196p293 197 487 196);"/>
                    <Edge cubics="!487 196(;487,196 486,36 486,36p487 196 486 36);"/>
                    <Edge cubics="!486 36(;486,36 293,37 293,37p486 36 293 37);"/>
                    <Edge cubics="!293 37(;293,37 293,7 293,7p293 37 293 7);"/>
                  </edges>
                </DOMShape>
                <DOMShape isDrawingObject="true">
                  <matrix>
                    <Matrix a="2.85386657714844" d="2.85386657714844" tx="14.85" ty="0.05"/>
                  </matrix>
                  <fills>
                    <FillStyle index="1">
                      <SolidColor color="#73400B"/>
                    </FillStyle>
                  </fills>
                  <edges>
                    <Edge fillStyle1="1" edges="!566 30|565 1!565 1|821 0!821 0|822 29!822 29[811 64 789 90!789 90[767 118 734 135!734 135|716 108!716 108[770 80 785 29!785 29|566 30!654 58|688 58!688 58[688 113 679 149!679 149[672 183 652 206!652 206[631 230 599 244!599 244|583 216
!583 216[611 204 626 185!626 185[640 168 648 137!648 137[654 107 654 58"/>
                    <Edge cubics="!654 58(654,58;654,58 688,58 688,58p654 58 688 58);"/>
                    <Edge cubics="!688 58(;688,95 685,125 679,149q688 58Q688 113q679 149)679,149;"/>
                    <Edge cubics="!679 149(679,149;674,173 664,192 652,206q679 149Q672 183q652 206)652,206;"/>
                    <Edge cubics="!652 206(652,206;639,221 622,234 599,244q652 206Q631 230q599 244)599,244;"/>
                    <Edge cubics="!599 244(599,244;599,244 583,216 583,216q599 244 583 216)583,216;"/>
                    <Edge cubics="!583 216(583,216;602,208 616,198 626,185q583 216Q611 204q626 185)626,185;"/>
                    <Edge cubics="!626 185(;636,173 643,157 648,137q626 185Q640 168q648 137)648,137;"/>
                    <Edge cubics="!648 137(648,137;652,117 654,90 654,58q648 137Q654 107q654 58);"/>
                    <Edge cubics="!566 30(566,30;566,30 565,1 565,1p566 30 565 1)565,1;"/>
                    <Edge cubics="!565 1(;565,1 821,0 821,0p565 1 821 0)821,0;"/>
                    <Edge cubics="!821 0(821,0;821,0 822,29 822,29q821 0 822 29);"/>
                    <Edge cubics="!822 29(;815,51 805,71 789,90q822 29Q811 64q789 90);"/>
                    <Edge cubics="!789 90(789,90;774,109 755,124 734,135q789 90Q767 118q734 135)734,135;"/>
                    <Edge cubics="!734 135(;734,135 716,108 716,108q734 135 716 108)716,108;"/>
                    <Edge cubics="!716 108(716,108;752,89 775,62 785,29q716 108Q770 80q785 29);"/>
                    <Edge cubics="!785 29(;785,29 566,30 566,30q785 29 566 30);"/>
                  </edges>
                </DOMShape>
              </elements>
            </DOMFrame>
          </frames>
        </DOMLayer>
      </layers>
    </DOMTimeline>
  </timeline>
</DOMSymbolItem>